api/__init__.py
api/apps.py
api/models.py
api/permissions.py
api/renderer.py
api/serializers.py
api/signals.py
api/urls.py
api/backend/__init__.py
api/backend/netapi.py
api/backend/pyapi.py
api/management/__init__.py
api/management/commands/__init__.py
api/management/commands/check.py
api/management/commands/current_version.py
api/management/commands/location.py
api/management/commands/manage_token.py
api/migrations/0001_initial.py
api/migrations/0002_jobtemplate.py
api/migrations/0003_auto_20200317_1719.py
api/migrations/__init__.py
api/migrations/usersettings.json
api/utils/__init__.py
api/utils/input/__init__.py
api/utils/output/__init__.py
api/utils/output/highstate_output.py
api/utils/output/nested_output.py
api/views/__init__.py
api/views/alcali.py
api/views/salt.py
bin/__init__.py
config/__init__.py
config/ldap_config.py
config/settings.py
config/social_config.py
config/urls.py
config/wsgi.py
dist/__init__.py
dist/index.html
dist/static/favicon.ico
dist/static/css/app.aed93e05.css
dist/static/css/chunk-vendors.fa4c09df.css
dist/static/fonts/MaterialIcons-Regular.0509ab09.woff2
dist/static/fonts/MaterialIcons-Regular.29b882f0.woff
dist/static/fonts/MaterialIcons-Regular.96c47680.eot
dist/static/fonts/MaterialIcons-Regular.da4ea5cd.ttf
dist/static/fonts/roboto-latin-100.5cb7edfc.woff
dist/static/fonts/roboto-latin-100.7370c367.woff2
dist/static/fonts/roboto-latin-100italic.f8b1df51.woff2
dist/static/fonts/roboto-latin-100italic.f9e8e590.woff
dist/static/fonts/roboto-latin-300.b00849e0.woff
dist/static/fonts/roboto-latin-300.ef7c6637.woff2
dist/static/fonts/roboto-latin-300italic.14286f3b.woff2
dist/static/fonts/roboto-latin-300italic.4df32891.woff
dist/static/fonts/roboto-latin-400.479970ff.woff2
dist/static/fonts/roboto-latin-400.60fa3c06.woff
dist/static/fonts/roboto-latin-400italic.51521a2a.woff2
dist/static/fonts/roboto-latin-400italic.fe65b833.woff
dist/static/fonts/roboto-latin-500.020c97dc.woff2
dist/static/fonts/roboto-latin-500.87284894.woff
alcali-3006.3.0.dist-info/LICENSE
alcali-3006.3.0.dist-info/METADATA
alcali-3006.3.0.dist-info/WHEEL
alcali-3006.3.0.dist-info/entry_points.txt
alcali-3006.3.0.dist-info/top_level.txt
alcali-3006.3.0.dist-info/RECORD
