Metadata-Version: 2.1
Name: alcali
Version: 3006.3.0
Summary: Alcali
Home-page: https://github.com/latenighttales/alcali.git
Author: Matt Melquiond
Author-email: matt.LLVW@gmail.com
License: UNKNOWN
Platform: UNKNOWN
Classifier: Programming Language :: Python :: 3
Classifier: License :: OSI Approved :: MIT License
Classifier: Operating System :: OS Independent
Classifier: Development Status :: 5 - Production/Stable
Classifier: Environment :: Web Environment
Classifier: Framework :: Django
Classifier: Intended Audience :: Developers
Classifier: Intended Audience :: Information Technology
Classifier: Intended Audience :: System Administrators
Classifier: Topic :: System :: Installation/Setup
Classifier: Topic :: System :: Systems Administration
Requires-Dist: ansi2html (==1.8.0)
Requires-Dist: Django (==4.2.5)
Requires-Dist: django-cors-headers (==4.2.0)
Requires-Dist: django-currentuser (==0.6.1)
Requires-Dist: djangorestframework (==3.14.0)
Requires-Dist: djangorestframework-simplejwt (==5.3.0)
Requires-Dist: gunicorn (==21.2.0)
Requires-Dist: PyJWT (==2.8.0)
Requires-Dist: python-dotenv (==1.0.0)
Requires-Dist: pytz
Requires-Dist: requests (==2.31.0)
Requires-Dist: salt-pepper (==0.7.6)
Requires-Dist: whitenoise (==6.5.0)
Provides-Extra: dev
Requires-Dist: black (==23.1a1) ; extra == 'dev'
Requires-Dist: django-extensions (==3.2.3) ; extra == 'dev'
Requires-Dist: ipython (==7.31.1) ; extra == 'dev'
Provides-Extra: ldap
Requires-Dist: django-auth-ldap (==4.5.0) ; extra == 'ldap'
Requires-Dist: python-ldap (==3.4.3) ; extra == 'ldap'
Provides-Extra: social
Requires-Dist: rest-social-auth (==8.1.0) ; extra == 'social'
